quantastica_qconvert-0.9.20-py3.9-nspkg.pth
quantastica/qconvert/__init__.py
quantastica/qconvert/convert.py
quantastica/qconvert/gate_defs.json
quantastica/qconvert/qconvert_base.py
quantastica/qconvert/qconvert_qobj.py
quantastica/qconvert/qobj_to_pyquil.py
quantastica/qconvert/qobj_to_toaster.py
tests/__init__.py
tests/test_convert.py
quantastica_qconvert-0.9.20.dist-info/LICENSE
quantastica_qconvert-0.9.20.dist-info/METADATA
quantastica_qconvert-0.9.20.dist-info/WHEEL
quantastica_qconvert-0.9.20.dist-info/namespace_packages.txt
quantastica_qconvert-0.9.20.dist-info/top_level.txt
quantastica_qconvert-0.9.20.dist-info/RECORD
