Metadata-Version: 2.1
Name: quantastica-qconvert
Version: 0.9.20
Summary: Quantastica quantum programming tools
Home-page: https://github.com/quantastica/qconvert
Author: Quantastica
Author-email: support@quantastica.com
License: Apache License 2.0
Platform: UNKNOWN
Classifier: Development Status :: 4 - Beta
Classifier: License :: OSI Approved :: Apache Software License
Classifier: Programming Language :: Python :: 3
Classifier: Intended Audience :: Science/Research
